[
    {
        "name": "Bobby Moahi",
        "email": "bobbymoahi@gmail.com",
        "tag": "General"
    },
    {
        "name": "Navan",
        "email": "navan@sirair.co.za",
        "tag": "Corporate A"
    },
    {
        "name": "Lawrence Moahi",
        "email": "lmoahi710@gmail.com",
        "tag": "General"
    },
    {
        "name": "Sales team at CTMG",
        "email": "sales@celsiustechmediagroup.co.za",
        "tag": "General"
    },
    {
        "name": "Info Celsius",
        "email": "info@celsiustechmediagroup.co.za",
        "tag": "General"
    },
    {
        "name": "Lawrence",
        "email": "info@hmpd.co.za",
        "tag": "General"
    },
      {
        "name": "a.kessenich",
        "email": "a.kessenich@northeastern.edu",
        "tag": "Corporate A"
    },
    {
        "name": "Smith",
        "email": "a.smith@usciences.edu",
        "tag": "Corporate A"
    },
    {
        "name": "aak618",
        "email": "aak618@lehigh.edu",
        "tag": "Corporate A"
    },
    {
        "name": "aanderson",
        "email": "aanderson@csbsju.edu",
        "tag": "Corporate A"
    },
    {
        "name": "aantanav",
        "email": "aantanav@jeffco.edu",
        "tag": "Corporate A"
    },
    {
        "name": "Aara",
        "email": "aaragon@oakton.edu",
        "tag": "Corporate A"
    },
    {
        "name": "aarbogast",
        "email": "aarbogast@lindenwood.edu",
        "tag": "Corporate A"
    },
    {
        "name": "aarce",
        "email": "aarce@csudh.edu",
        "tag": "Corporate A"
    },
    {
        "name": "Aaron",
        "email": "aaron.hastings@unt.edu",
        "tag": "Corporate A"
    },
    {
        "name": "Aaron",
        "email": "aaron.mansfield@lmu.edu",
        "tag": "Corporate A"
    },
    {
        "name": "Aaron",
        "email": "aaron_hedland1@vcccd.edu",
        "tag": "Corporate A"
    },
    {
        "name": "aassimos",
        "email": "aassimos@dom.edu",
        "tag": "Corporate A"
    },
    {
        "name": "aatnip01",
        "email": "aatnip01@clevelandstatecc.edu",
        "tag": "Corporate A"
    },
    {
        "name": "aawilliams",
        "email": "aawilliams@iwcc.edu",
        "tag": "Corporate A"
    },
    {
        "name": "Aba",
        "email": "abarmore@transy.edu",
        "tag": "Corporate A"
    },
    {
        "name": "Aba",
        "email": "abaustin1@liberty.edu",
        "tag": "Corporate A"
    },
    {
        "name": "Abbey",
        "email": "abbey.wehrman@ojc.edu",
        "tag": "Corporate A"
    },
    {
        "name": "Abbey",
        "email": "abbey_troy@sac.edu",
        "tag": "Corporate A"
    },
    {
        "name": "Abby",
        "email": "abby.crowser@minnesota.edu",
        "tag": "Corporate A"
    },
    {
        "name": "Abby",
        "email": "abby.gilleland@uconn.edu",
        "tag": "Corporate A"
    },
    {
        "name": "Abdul",
        "email": "abdul.chamma@northlandcollege.edu",
        "tag": "Corporate A"
    },
    {
        "name": "Abe",
        "email": "abecerra@lec.edu",
        "tag": "Corporate A"
    },
    {
        "name": "Abe",
        "email": "abegger@dawson.edu",
        "tag": "Corporate A"
    },
    {
        "name": "Aben",
        "email": "abenning@sports.uga.edu",
        "tag": "Corporate A"
    },
    {
        "name": "Aber",
        "email": "aberkley@luc.edu",
        "tag": "Corporate A"
    },
    {
        "name": "Aber",
        "email": "aberry@caldwell.edu",
        "tag": "Corporate A"
    },
    {
        "name": "Abey",
        "email": "abeyer@gsu.edu",
        "tag": "Corporate A"
    },
    {
        "name": "abfuller",
        "email": "abfuller@stanford.edu",
        "tag": "Corporate A"
    },
    {
        "name": "Abiel",
        "email": "abielby@cscc.edu",
        "tag": "Corporate A"
    },
    {
        "name": "Abigail",
        "email": "abigail.saehler@gcu.edu",
        "tag": "Corporate A"
    },
    {
        "name": "Abigail",
        "email": "abigail.screnock@lawrence.edu",
        "tag": "Corporate A"
    },
    {
        "name": "Abir",
        "email": "abird@colgate.edu",
        "tag": "Corporate A"
    },
    {
        "name": "Abla",
        "email": "ablack@vcccd.edu",
        "tag": "Corporate A"
    },
    {
        "name": "Abla",
        "email": "ablair2@umassd.edu",
        "tag": "Corporate A"
    },
    {
        "name": "abohne",
        "email": "abohne@rollins.edu",
        "tag": "Corporate A"
    },
    {
        "name": "Abra",
        "email": "abraun@oglethorpe.edu",
        "tag": "Corporate A"
    },
    {
        "name": "abroccoli",
        "email": "abroccoli@drew.edu",
        "tag": "Corporate A"
    },
    {
        "name": "Abu",
        "email": "abuchanan@ucdavis.edu",
        "tag": "Corporate A"
    },
    {
        "name": "Abu",
        "email": "abuffham@masters.edu",
        "tag": "Corporate A"
    },
    {
        "name": "Abu",
        "email": "abullard@nctc.edu",
        "tag": "Corporate A"
    },
    {
        "name": "Abu",
        "email": "aburchyett@northwestms.edu",
        "tag": "Corporate A"
    },
    {
        "name": "acampbell",
        "email": "acampbell@umobile.edu",
        "tag": "Corporate A"
    },
    {
        "name": "acapone",
        "email": "acapone@hamilton.edu",
        "tag": "Corporate A"
    },
    {
        "name": "acarrizales",
        "email": "acarrizales@yvcc.edu",
        "tag": "Corporate A"
    },
    {
        "name": "acd225",
        "email": "acd225@cornell.edu",
        "tag": "Corporate A"
    },
    {
        "name": "Ace",
        "email": "acewalt@olivet.edu",
        "tag": "Corporate A"
    },
    {
        "name": "acooke",
        "email": "acooke@bgsu.edu",
        "tag": "Corporate A"
    },
    {
        "name": "acoyle",
        "email": "acoyle@ohiochristian.edu",
        "tag": "Corporate A"
    },
    {
        "name": "acrimes",
        "email": "acrimes@calstatela.edu",
        "tag": "Corporate A"
    },
    {
        "name": "acrowder",
        "email": "acrowder@fit.edu",
        "tag": "Corporate A"
    },
    {
        "name": "Adai",
        "email": "adai@lesley.edu",
        "tag": "Corporate A"
    },
    {
        "name": "Adamo",
        "email": "adamore@udel.edu",
        "tag": "Corporate A"
    },
    {
        "name": "Adams",
        "email": "adamsry@lafayette.edu",
        "tag": "Corporate A"
    },
    {
        "name": "Ada",
        "email": "adavis@masters.edu",
        "tag": "Corporate A"
    },
    {
        "name": "Adea",
        "email": "adeal@santarosa.edu",
        "tag": "Corporate A"
    },
    {
        "name": "Adel",
        "email": "adeloid@stevens.edu",
        "tag": "Corporate A"
    },
    {
        "name": "Adel",
        "email": "adelpio@bgsu.edu",
        "tag": "Corporate A"
    },
    {
        "name": "Ader",
        "email": "aderrico1@udayton.edu",
        "tag": "Corporate A"
    },
    {
        "name": "Ade",
        "email": "adeterin@kent.edu",
        "tag": "Corporate A"
    },
    {
        "name": "Adlee",
        "email": "adleevanwinden@ucsb.edu",
        "tag": "Corporate A"
    },
    {
        "name": "Ado",
        "email": "adoerfler@linfield.edu",
        "tag": "Corporate A"
    },
    {
        "name": "Adriana",
        "email": "adriana.skipper@ottawa.edu",
        "tag": "Corporate A"
    },
    {
        "name": "Adrianna",
        "email": "Adrianna.Culbert@colostate.edu",
        "tag": "Corporate A"
    },
    {
        "name": "Adriano",
        "email": "adriano.desouza@mail.wvu.edu",
        "tag": "Corporate A"
    },
    {
        "name": "Adric",
        "email": "adrichardson@wesleyancollege.edu",
        "tag": "Corporate A"
    },
    {
        "name": "adunn",
        "email": "adunn@uwlax.edu",
        "tag": "Corporate A"
    },
    {
        "name": "aea11",
        "email": "aea11@stmarys-ca.edu",
        "tag": "Corporate A"
    },
    {
        "name": "aeb14",
        "email": "aeb14@stmarys-ca.edu",
        "tag": "Corporate A"
    },
    {
        "name": "AElsbernd",
        "email": "AElsbernd@dbq.edu",
        "tag": "Corporate A"
    },
    {
        "name": "aemanuel",
        "email": "aemanuel@fisk.edu",
        "tag": "Corporate A"
    },
    {
        "name": "aemiller",
        "email": "aemiller@bryantstratton.edu",
        "tag": "Corporate A"
    },
    {
        "name": "Aerick",
        "email": "aerickson2@uca.edu",
        "tag": "Corporate A"
    },
    {
        "name": "aeveach",
        "email": "aeveach@uab.edu",
        "tag": "Corporate A"
    },
    {
        "name": "afahey",
        "email": "afahey@su.suffolk.edu",
        "tag": "Corporate A"
    },
    {
        "name": "aganus",
        "email": "aganus@marshall.edu",
        "tag": "Corporate A"
    },
    {
        "name": "aglinville",
        "email": "aglinville@mail.wvu.edu",
        "tag": "Corporate A"
    },
    {
        "name": "agoldsberry",
        "email": "agoldsberry@seu.edu",
        "tag": "Corporate A"
    },
    {
        "name": "agormanson",
        "email": "agormanson@olympic.edu",
        "tag": "Corporate A"
    },
    {
        "name": "agregory",
        "email": "agregory@bellarmine.edu",
        "tag": "Corporate A"
    },
    {
        "name": "aguerci",
        "email": "aguerci@fiu.edu",
        "tag": "Corporate A"
    },
    {
        "name": "ahain",
        "email": "ahain@uci.edu",
        "tag": "Corporate A"
    },
    {
        "name": "Ahan",
        "email": "ahanley@schreiner.edu",
        "tag": "Corporate A"
    },
    {
        "name": "aheffele",
        "email": "aheffele@lee.edu",
        "tag": "Corporate A"
    },
    {
        "name": "aheinz",
        "email": "aheinz@methodist.edu",
        "tag": "Corporate A"
    },
    {
        "name": "aheld2",
        "email": "aheld2@kennesaw.edu",
        "tag": "Corporate A"
    },
    {
        "name": "Kim",
        "email": "ahen_kim@brown.edu",
        "tag": "Corporate A"
    },
    {
        "name": "aherron",
        "email": "aherron@kckcc.edu",
        "tag": "Corporate A"
    },
    {
        "name": "ahinsey",
        "email": "ahinsey@umw.edu",
        "tag": "Corporate A"
    },
    {
        "name": "ahodgson",
        "email": "ahodgson@ocean.edu",
        "tag": "Corporate A"
    },
    {
        "name": "ahoekstr",
        "email": "ahoekstr@shepherd.edu",
        "tag": "Corporate A"
    },
    {
        "name": "ailkson",
        "email": "ailkson@gmu.edu",
        "tag": "Corporate A"
    },
    {
        "name": "Aja",
        "email": "ajackson@suscc.edu",
        "tag": "Corporate A"
    },
    {
        "name": "Aja",
        "email": "ajackson23@sierracollege.edu",
        "tag": "Corporate A"
    },
    {
        "name": "Aje",
        "email": "ajeffrey@iwcc.edu",
        "tag": "Corporate A"
    },
    {
        "name": "ajgage",
        "email": "ajgage@trevecca.edu",
        "tag": "Corporate A"
    },
    {
        "name": "AJLeonard",
        "email": "AJLeonard@ship.edu",
        "tag": "Corporate A"
    },
    {
        "name": "ajlux",
        "email": "ajlux@missouristate.edu",
        "tag": "Corporate A"
    },
    {
        "name": "ajjohnson3",
        "email": "ajjohnson3@cau.edu",
        "tag": "Corporate A"
    },
    {
        "name": "Ajon",
        "email": "ajonesolson@ccis.edu",
        "tag": "Corporate A"
    },
    {
        "name": "ajordan3",
        "email": "ajordan3@washcoll.edu",
        "tag": "Corporate A"
    },
    {
        "name": "ajpollart",
        "email": "ajpollart@umary.edu",
        "tag": "Corporate A"
    },
    {
        "name": "ak4237",
        "email": "ak4237@columbia.edu",
        "tag": "Corporate A"
    },
    {
        "name": "Akeem",
        "email": "akeem.bonepart@claflin.edu",
        "tag": "Corporate A"
    },
    {
        "name": "Aking",
        "email": "aking5@stetson.edu",
        "tag": "Corporate A"
    },
    {
        "name": "Aki",
        "email": "akish@ccp.edu",
        "tag": "Corporate A"
    },
    {
        "name": "akpittenger",
        "email": "akpittenger@loyola.edu",
        "tag": "Corporate A"
    },
    {
        "name": "Akram",
        "email": "akramer@carleton.edu",
        "tag": "Corporate A"
    },
    {
        "name": "akroger",
        "email": "akroger@una.edu",
        "tag": "Corporate A"
    },
    {
        "name": "Alaa",
        "email": "alaatsch@belhaven.edu",
        "tag": "Corporate A"
    },
    {
        "name": "Alam",
        "email": "Alamberson@marymountcalifornia.edu",
        "tag": "Corporate A"
    },
    {
        "name": "Albana",
        "email": "albana.munrett@purchase.edu",
        "tag": "Corporate A"
    },
    {
        "name": "Alda",
        "email": "aldavis079@my.pittcc.edu",
        "tag": "Corporate A"
    },
    {
        "name": "Aleah",
        "email": "Aleah.hayes@tvcc.edu",
        "tag": "Corporate A"
    },
    {
        "name": "Alea",
        "email": "aleake@bethelks.edu",
        "tag": "Corporate A"
    },
    {
        "name": "Aleesha",
        "email": "aleesha.cleaver@wmpenn.edu",
        "tag": "Corporate A"
    },
    {
        "name": "Ale",
        "email": "alegonza@nmu.edu",
        "tag": "Corporate A"
    },
    {
        "name": "Ale",
        "email": "alehocky@nmjc.edu",
        "tag": "Corporate A"
    },
    {
        "name": "Alejandra",
        "email": "alejandra.jimenez@kwc.edu",
        "tag": "Corporate A"
    },
    {
        "name": "Alela",
        "email": "alelaus@email.ecok.edu",
        "tag": "Corporate A"
    },
    {
        "name": "Aleona",
        "email": "aleonard@csusm.edu",
        "tag": "Corporate A"
    },
    {
        "name": "Alesha",
        "email": "Alesha.J.Wilson@dartmouth.edu",
        "tag": "Corporate A"
    },
    {
        "name": "Alexander",
        "email": "alexander.czopek@wilkes.edu",
        "tag": "Corporate A"
    },
    {
        "name": "Alexander",
        "email": "alexander.gordon.1@minotstateu.edu",
        "tag": "Corporate A"
    },
    {
        "name": "Alexandria",
        "email": "alexandria.dowdall@mcc.edu",
        "tag": "Corporate A"
    },
    {
        "name": "Alexan",
        "email": "alexanmk01@sunyjcc.edu",
        "tag": "Corporate A"
    },
    {
        "name": "Alexe",
        "email": "alexenavarro@multnomah.edu",
        "tag": "Corporate A"
    },
    {
        "name": "Alexis",
        "email": "alexis.carson@sw.edu",
        "tag": "Corporate A"
    },
    {
        "name": "Alexis",
        "email": "Alexis.N.Garrison@evergreen.edu",
        "tag": "Corporate A"
    },
    {
        "name": "Alexis",
        "email": "alexisi@mailbox.sc.edu",
        "tag": "Corporate A"
    },
    {
        "name": "Alex",
        "email": "alexvenardos@boisestate.edu",
        "tag": "Corporate A"
    },
    {
        "name": "Alfa",
        "email": "alfalcon@iu.edu",
        "tag": "Corporate A"
    },
    {
        "name": "Alicia",
        "email": "alicia.wood@ic.edu",
        "tag": "Corporate A"
    },
    {
        "name": "Ali",
        "email": "alilliquist@sjcny.edu",
        "tag": "Corporate A"
    },
    {
        "name": "Alim",
        "email": "alimccolloch@ucdavis.edu",
        "tag": "Corporate A"
    },
    {
        "name": "Alison",
        "email": "alison.williams@lmunet.edu",
        "tag": "Corporate A"
    },
    {
        "name": "Ali",
        "email": "alitrenta@albright.edu",
        "tag": "Corporate A"
    },
    {
        "name": "Aliyah",
        "email": "aliyah@fortscott.edu",
        "tag": "Corporate A"
    },
    {
        "name": "Alli",
        "email": "alli.obanion@neo.edu",
        "tag": "Corporate A"
    },
    {
        "name": "Allie",
        "email": "allie.matters@wright.edu",
        "tag": "Corporate A"
    },
    {
        "name": "Allie",
        "email": "Allieboo6296@gmail.com",
        "tag": "Corporate A"
    },
    {
        "name": "Allison",
        "email": "allison.lawrence@mso.umt.edu",
        "tag": "Corporate A"
    },
    {
        "name": "Allison",
        "email": "Allison.Volkmer@victoriacollege.edu",
        "tag": "Corporate A"
    },
    {
        "name": "Allison",
        "email": "allison.yaeger@shu.edu",
        "tag": "Corporate A"
    },
    {
        "name": "Allison",
        "email": "allisonbuck@boisestate.edu",
        "tag": "Corporate A"
    },
    {
        "name": "Allison",
        "email": "AllisonKuster@letu.edu",
        "tag": "Corporate A"
    },
    {
        "name": "Allyne",
        "email": "allyne@ncsu.edu",
        "tag": "Corporate A"
    },
    {
        "name": "Alma",
        "email": "alma.kovaci@westpoint.edu",
        "tag": "Corporate A"
    },
    {
        "name": "alrodriguez",
        "email": "alrodriguez@northwestern.edu",
        "tag": "Corporate A"
    },
    {
        "name": "Alyssa",
        "email": "alyssa.baumhover@clarke.edu",
        "tag": "Corporate A"
    },
    {
        "name": "Alyssa",
        "email": "alyssa.shores@salem.edu",
        "tag": "Corporate A"
    },
    {
        "name": "Alyssa",
        "email": "alyssa.whitney@oregonstate.edu",
        "tag": "Corporate A"
    },
    {
        "name": "Alyssa",
        "email": "alyssa-klostermann@iowavolleyball.com",
        "tag": "Corporate A"
    },
    {
        "name": "Ama",
        "email": "amackin@jessup.edu",
        "tag": "Corporate A"
    },
    {
        "name": "Ama",
        "email": "amaclean@uca.edu",
        "tag": "Corporate A"
    },
    {
        "name": "Ama",
        "email": "amahan@rangercollege.edu",
        "tag": "Corporate A"
    },
    {
        "name": "Amal",
        "email": "amalchoff@haskell.edu",
        "tag": "Corporate A"
    },
    {
        "name": "Amanda",
        "email": "amanda.chamberlain@unt.edu",
        "tag": "Corporate A"
    },
    {
        "name": "Amanda",
        "email": "amanda.huber@blc.edu",
        "tag": "Corporate A"
    },
    {
        "name": "Amanda",
        "email": "amanda.vazquez@chaminade.edu",
        "tag": "Corporate A"
    },
    {
        "name": "Amanda",
        "email": "amanda.wilkins@mville.edu",
        "tag": "Corporate A"
    },
    {
        "name": "Amanda",
        "email": "amandaglaza@grcc.edu",
        "tag": "Corporate A"
    },
    {
        "name": "Amanda",
        "email": "amandas@northeast.edu",
        "tag": "Corporate A"
    },
    {
        "name": "Amanda",
        "email": "amandasnyder@ccu.edu",
        "tag": "Corporate A"
    },
    {
        "name": "Amar",
        "email": "amarsellis@oru.edu",
        "tag": "Corporate A"
    },
    {
        "name": "Amar",
        "email": "amartinez8@sfc.edu",
        "tag": "Corporate A"
    },
    {
        "name": "amb24",
        "email": "amb24@nyu.edu",
        "tag": "Corporate A"
    },
    {
        "name": "Amber",
        "email": "amber.haver@ciu.edu",
        "tag": "Corporate A"
    },
    {
        "name": "Amber",
        "email": "amberwitherspoon@dbq.edu",
        "tag": "Corporate A"
    },
    {
        "name": "amccray",
        "email": "amccray@latech.edu",
        "tag": "Corporate A"
    },
    {
        "name": "amccreary",
        "email": "amccreary@academyart.edu",
        "tag": "Corporate A"
    },
    {
        "name": "amcdonough",
        "email": "amcdonough@centenary.edu",
        "tag": "Corporate A"
    },
    {
        "name": "amcgahan",
        "email": "amcgahan@fitchburgstate.edu",
        "tag": "Corporate A"
    },
    {
        "name": "amclamb",
        "email": "amclamb@odu.edu",
        "tag": "Corporate A"
    },
    {
        "name": "Ame",
        "email": "amezacapa@ndc.edu",
        "tag": "Corporate A"
    },
    {
        "name": "Amile",
        "email": "amilewski@lynn.edu",
        "tag": "Corporate A"
    },
    {
        "name": "Amil",
        "email": "amiller@cottey.edu",
        "tag": "Corporate A"
    },
    {
        "name": "Ammar",
        "email": "ammartinez5@miners.utep.edu",
        "tag": "Corporate A"
    },
    {
        "name": "Amo",
        "email": "amooney@acu.edu",
        "tag": "Corporate A"
    },
    {
        "name": "Amoura",
        "email": "amoura@uca.edu",
        "tag": "Corporate A"
    },
    {
        "name": "amscott07",
        "email": "amscott07@ysu.edu",
        "tag": "Corporate A"
    },
    {
        "name": "amugler",
        "email": "amugler@murraystate.edu",
        "tag": "Corporate A"
    },
    {
        "name": "amv",
        "email": "amv@tompkinscortland.edu",
        "tag": "Corporate A"
    },
]
